DSBA_Final.py
__init__.py
DSBA_Final-0.1.9.dist-info/METADATA
DSBA_Final-0.1.9.dist-info/WHEEL
DSBA_Final-0.1.9.dist-info/top_level.txt
DSBA_Final-0.1.9.dist-info/zip-safe
DSBA_Final-0.1.9.dist-info/RECORD
